README.md
setup.py
TOPSIS/__init__.py
TOPSIS/topsis.py
TOPSIS_Nikhal_101816034.egg-info/PKG-INFO
TOPSIS_Nikhal_101816034.egg-info/SOURCES.txt
TOPSIS_Nikhal_101816034.egg-info/dependency_links.txt
TOPSIS_Nikhal_101816034.egg-info/top_level.txt