Metadata-Version: 2.1
Name: TOPSIS-Nikhal-101816034
Version: 0.0.1
Summary: Python Package Implementing TOPSIS (for finding ideal and anti-ideal solution)
Home-page: https://github.com/Nik404/Topsis-Package
Author: Nikhal Singh
License: UNKNOWN
Platform: UNKNOWN
Classifier: Programming Language :: Python :: 3
Classifier: License :: OSI Approved :: MIT License
Classifier: Operating System :: OS Independent
Requires-Python: >=3.6
